GAO/GAO.py
GAO-0.1.8.dist-info/METADATA
GAO-0.1.8.dist-info/WHEEL
GAO-0.1.8.dist-info/top_level.txt
GAO-0.1.8.dist-info/RECORD
