Metadata-Version: 2.1
Name: GAO
Version: 0.1.8
Summary: Gis Application Objects
Author: Gao Zhiheng
Author-email: 11279470@qq.com
